HyperledgerYuanmaFenxiZhiFabric/README.md
HyperledgerYuanmaFenxiZhiFabric/__init__.py
HyperledgerYuanmaFenxiZhiFabric/__main__.py
HyperledgerYuanmaFenxiZhiFabric/file.epub
HyperledgerYuanmaFenxiZhiFabric/index.html
HyperledgerYuanmaFenxiZhiFabric/css/__init__.py
HyperledgerYuanmaFenxiZhiFabric/css/annotations.css
HyperledgerYuanmaFenxiZhiFabric/css/main.css
HyperledgerYuanmaFenxiZhiFabric/css/normalize.css
HyperledgerYuanmaFenxiZhiFabric/css/popup.css
HyperledgerYuanmaFenxiZhiFabric/font/__init__.py
HyperledgerYuanmaFenxiZhiFabric/font/fontello.eot
HyperledgerYuanmaFenxiZhiFabric/font/fontello.svg
HyperledgerYuanmaFenxiZhiFabric/font/fontello.ttf
HyperledgerYuanmaFenxiZhiFabric/font/fontello.woff
HyperledgerYuanmaFenxiZhiFabric/img/__init__.py
HyperledgerYuanmaFenxiZhiFabric/img/annotator-glyph-sprite.png
HyperledgerYuanmaFenxiZhiFabric/img/annotator-icon-sprite.png
HyperledgerYuanmaFenxiZhiFabric/img/apple-touch-icon.png
HyperledgerYuanmaFenxiZhiFabric/img/cancelfullscreen.png
HyperledgerYuanmaFenxiZhiFabric/img/close.png
HyperledgerYuanmaFenxiZhiFabric/img/fullscreen.png
HyperledgerYuanmaFenxiZhiFabric/img/loader.gif
HyperledgerYuanmaFenxiZhiFabric/img/menu-icon.png
HyperledgerYuanmaFenxiZhiFabric/img/save.png
HyperledgerYuanmaFenxiZhiFabric/img/saved.png
HyperledgerYuanmaFenxiZhiFabric/img/settings-s.png
HyperledgerYuanmaFenxiZhiFabric/img/settings.png
HyperledgerYuanmaFenxiZhiFabric/img/star.png
HyperledgerYuanmaFenxiZhiFabric/js/__init__.py
HyperledgerYuanmaFenxiZhiFabric/js/epub.js
HyperledgerYuanmaFenxiZhiFabric/js/epub.min.js
HyperledgerYuanmaFenxiZhiFabric/js/epub.min.map
HyperledgerYuanmaFenxiZhiFabric/js/hooks.min.js
HyperledgerYuanmaFenxiZhiFabric/js/hooks.min.map
HyperledgerYuanmaFenxiZhiFabric/js/reader.js
HyperledgerYuanmaFenxiZhiFabric/js/reader.js.map
HyperledgerYuanmaFenxiZhiFabric/js/reader.min.js
HyperledgerYuanmaFenxiZhiFabric/js/reader.min.map
HyperledgerYuanmaFenxiZhiFabric/js/hooks/__init__.py
hyperledger_yuanma_fenxi_zhi_fabric-2024.3.2.0.dist-info/METADATA
hyperledger_yuanma_fenxi_zhi_fabric-2024.3.2.0.dist-info/WHEEL
hyperledger_yuanma_fenxi_zhi_fabric-2024.3.2.0.dist-info/entry_points.txt
hyperledger_yuanma_fenxi_zhi_fabric-2024.3.2.0.dist-info/top_level.txt
hyperledger_yuanma_fenxi_zhi_fabric-2024.3.2.0.dist-info/RECORD
